{
  "function": "minecraft:set_written_book_pages",
  "pages": [
    [
{"text":"","font": "minecraft:alt"}, {"text":"B","font": "minecraft:default"}, {"text":"reach is a devastating mace enchantment designed to pierce through defenses","font": "minecraft:alt"}, {"text":",","font": "minecraft:default"}, {"text":" systematically diminishing the effectiveness of an opponent","font": "minecraft:alt"}, {"text":"'","font": "minecraft:default"}, {"text":"s armor","font": "minecraft:alt"}, {"text":".","font": "minecraft:default"}, {"text":" ","font": "minecraft:alt"}, {"text":"T","font": "minecraft:default"}, {"text":"his effect compromises all forms of armor worn by entities","font": "minecraft:alt"}, {"text":",","font": "minecraft:default"}, {"text":" as well as the inherent natural armor","font": "minecraft:alt"}, {"text":".","font": "minecraft:default"}]
  ],
  "mode": "append"
}