{
  "function": "minecraft:set_written_book_pages",
  "pages": [
    [
{"text":"","font": "minecraft:alt"}, {"text":"U","font": "minecraft:default"}, {"text":"nbreaking","font": "minecraft:alt"}, {"text":",","font": "minecraft:default"}, {"text":" an enchantment of preservation","font": "minecraft:alt"}, {"text":",","font": "minecraft:default"}, {"text":" is woven into items to fortify their resilience","font": "minecraft:alt"}, {"text":".","font": "minecraft:default"}, {"text":" ","font": "minecraft:alt"}, {"text":"T","font": "minecraft:default"}, {"text":"his grants the item an extended lifespan","font": "minecraft:alt"}, {"text":",","font": "minecraft:default"}, {"text":" a testament to the enchantment","font": "minecraft:alt"}, {"text":"'","font": "minecraft:default"}, {"text":"s power to ward off the inevitable erosion of its essence","font": "minecraft:alt"}, {"text":".","font": "minecraft:default"}]
  ],
  "mode": "append"
}